english_date_as_bangla_format/__init__.py
english_date_as_bangla_format/en_to_bn_dateformat_converter.py
english_date_as_bangla_format-0.0.1.dist-info/LICENSE
english_date_as_bangla_format-0.0.1.dist-info/METADATA
english_date_as_bangla_format-0.0.1.dist-info/WHEEL
english_date_as_bangla_format-0.0.1.dist-info/top_level.txt
english_date_as_bangla_format-0.0.1.dist-info/RECORD
